gplugins/__init__.py
gplugins/typings.py
gplugins/common/__init__.py
gplugins/common/config.py
gplugins/common/types.py
gplugins/common/base_models/__init__.py
gplugins/common/base_models/component.py
gplugins/common/base_models/simulation.py
gplugins/common/utils/__init__.py
gplugins/common/utils/add_simulation_markers.py
gplugins/common/utils/async_helpers.py
gplugins/common/utils/cache.py
gplugins/common/utils/convert_sparameters.py
gplugins/common/utils/disable_print.py
gplugins/common/utils/geometry.py
gplugins/common/utils/get_capacitance.py
gplugins/common/utils/get_component_with_net_layers.py
gplugins/common/utils/get_effective_indices.py
gplugins/common/utils/get_scattering.py
gplugins/common/utils/get_sparameters_path.py
gplugins/common/utils/optical_constants.py
gplugins/common/utils/parse_layer_stack.py
gplugins/common/utils/plot.py
gplugins/common/utils/plot_csv.py
gplugins/common/utils/port_symmetries.py
gplugins/common/utils/tests/test_get_component_with_new_port_layers.py
gplugins/devsim/__init__.py
gplugins/devsim/doping.py
gplugins/devsim/get_simulation.py
gplugins/devsim/get_simulation_xsection.py
gplugins/devsim/get_solver.py
gplugins/devsim/test_devsim.py
gplugins/elmer/__init__.py
gplugins/elmer/electrostatic.sif.j2
gplugins/elmer/get_capacitance.py
gplugins/elmer/tests/test_elmer.py
gplugins/fdtdz/__init__.py
gplugins/fdtdz/get_epsilon_fdtdz.py
gplugins/fdtdz/get_ports_fdtdz.py
gplugins/fdtdz/get_sparameters_fdtdz.py
gplugins/femwell/__init__.py
gplugins/femwell/mode_solver.py
gplugins/femwell/solve_thermal.py
gplugins/femwell/test_mode_solver.py
gplugins/gfviz/Makefile
gplugins/gfviz/__init__.py
gplugins/gfviz/b64.py
gplugins/gfviz/gfviz.py
gplugins/gfviz/netlist.py
gplugins/gfviz/serve.py
gplugins/gfviz/static/b64.js
gplugins/gfviz/static/schemedit.js
gplugins/gfviz/static/schemedit.wasm
gplugins/gfviz/templates/example.json
gplugins/gfviz/templates/index.html
gplugins/gmeep/__init__.py
gplugins/gmeep/get_material.py
gplugins-2.0.1.dist-info/licenses/LICENSE
gplugins-2.0.1.dist-info/WHEEL
gplugins-2.0.1.dist-info/METADATA
gplugins-2.0.1.dist-info/RECORD
